django_no_lazy_queries-0.1.dist-info/DESCRIPTION.rst
django_no_lazy_queries-0.1.dist-info/METADATA
django_no_lazy_queries-0.1.dist-info/RECORD
django_no_lazy_queries-0.1.dist-info/WHEEL
django_no_lazy_queries-0.1.dist-info/metadata.json
django_no_lazy_queries-0.1.dist-info/top_level.txt
nolazyqueries/__init__.py
