Metadata-Version: 2.0
Name: django-no-lazy-queries
Version: 0.1
Summary: Prevent Django from automatically loading related models
Home-page: https://github.com/terite/django-no-lazy-queries
Author: David Stensland
Author-email: nolazyqueries@terite.com
License: UNKNOWN
Download-URL: https://pypi.python.org/pypi/django-no-lazy-queries
Platform: UNKNOWN
Classifier: Environment :: Web Environment
Classifier: Framework :: Django
Classifier: Intended Audience :: Developers
Classifier: Operating System :: OS Independent
Classifier: Programming Language :: Python
Classifier: Programming Language :: Python :: 2
Classifier: Programming Language :: Python :: 2.7
Classifier: Programming Language :: Python :: 3
Classifier: Programming Language :: Python :: 3.4
Classifier: Programming Language :: Python :: 3.5
Requires-Dist: Django (>=1.8)
Requires-Dist: contextlib2
